{
  "baseline_bald": {
    "experiment_name": "baseline_bald",
    "description": "BALD采样基线",
    "performance_history": [
      {
        "round": 1,
        "mIoU": 0.6445679925815234,
        "f1_score": 0.7313532895361122,
        "labeled_size": 151
      },
      {
        "round": 2,
        "mIoU": 0.6811647947889994,
        "f1_score": 0.7711784744324948,
        "labeled_size": 239
      },
      {
        "round": 3,
        "mIoU": 0.7141223974152099,
        "f1_score": 0.8038250526933823,
        "labeled_size": 327
      },
      {
        "round": 4,
        "mIoU": 0.7377404789450005,
        "f1_score": 0.8254450098405177,
        "labeled_size": 415
      },
      {
        "round": 5,
        "mIoU": 0.7236890011323789,
        "f1_score": 0.8126417095181253,
        "labeled_size": 503
      },
      {
        "round": 6,
        "mIoU": 0.7436861907597538,
        "f1_score": 0.8309434677161194,
        "labeled_size": 591
      },
      {
        "round": 7,
        "mIoU": 0.7564855400044113,
        "f1_score": 0.8417740600442822,
        "labeled_size": 679
      },
      {
        "round": 8,
        "mIoU": 0.7580770547804583,
        "f1_score": 0.8431429249341054,
        "labeled_size": 767
      },
      {
        "round": 9,
        "mIoU": 0.7563536134992336,
        "f1_score": 0.8417211164759901,
        "labeled_size": 855
      },
      {
        "round": 10,
        "mIoU": 0.7506939585930341,
        "f1_score": 0.8367747932485172,
        "labeled_size": 943
      },
      {
        "round": 11,
        "mIoU": 0.7561583209208447,
        "f1_score": 0.8414002255916209,
        "labeled_size": 1031
      },
      {
        "round": 12,
        "mIoU": 0.7667676461117695,
        "f1_score": 0.8503310912405453,
        "labeled_size": 1119
      },
      {
        "round": 13,
        "mIoU": 0.7620356228939974,
        "f1_score": 0.8463484632434687,
        "labeled_size": 1207
      },
      {
        "round": 14,
        "mIoU": 0.7551455846116003,
        "f1_score": 0.8404290711791345,
        "labeled_size": 1295
      },
      {
        "round": 15,
        "mIoU": 0.7557757580997643,
        "f1_score": 0.8411738007538785,
        "labeled_size": 1383
      }
    ],
    "budget_history": [
      151,
      239,
      327,
      415,
      503,
      591,
      679,
      767,
      855,
      943,
      1031,
      1119,
      1207,
      1295,
      1383
    ],
    "fallback_history": [],
    "alc": 0.667983677500812,
    "final_miou": 0.7557757580997643,
    "final_f1": 0.8411738007538785,
    "epochs_schedule_source": null,
    "epochs_schedule": null,
    "status": "success",
    "timestamp": "2026-03-01T21:00:14.687461",
    "log_file": "results/logs_md/baseline_bald_baseline_20260228_124857_seed45.md"
  }
}